LICENSE
MANIFEST.in
README.md
setup.cfg
setup.py
src/py_event_mocks/__init__.py
src/py_event_mocks/events.py
src/py_event_mocks.egg-info/PKG-INFO
src/py_event_mocks.egg-info/SOURCES.txt
src/py_event_mocks.egg-info/dependency_links.txt
src/py_event_mocks.egg-info/requires.txt
src/py_event_mocks.egg-info/top_level.txt
src/py_event_mocks/events/aws/alexa-skill-event-template.json
src/py_event_mocks/events/aws/alexa-smart-home-event-template.json
src/py_event_mocks/events/aws/api-gateway-event-template.json
src/py_event_mocks/events/aws/batcb-event-template.json
src/py_event_mocks/events/aws/cloud-watch-event-template.json
src/py_event_mocks/events/aws/cloud-watch-log-event-template.json
src/py_event_mocks/events/aws/cognito-user-pool-event-template.json
src/py_event_mocks/events/aws/dynamo-stream-event-template.json
src/py_event_mocks/events/aws/kinesis-template.json
src/py_event_mocks/events/aws/s3-template.json
src/py_event_mocks/events/aws/scheduled-template.json
src/py_event_mocks/events/aws/sns-template.json
src/py_event_mocks/events/aws/sqs-template.json