Metadata-Version: 2.1
Name: py-event-mocks
Version: 0.0.4
Summary: A small library that includes details mocks of AWS Lambda event sources, Python implementation.
Home-page: https://github.com/smatsumt/py-event-mocks
Author: Shinji Matsumoto
Author-email: shinji.mtsmt@gmail.com
License: MIT
Platform: UNKNOWN
